README.md
setup.py
salesforce/__init__.py
salesforce_wrapper.egg-info/PKG-INFO
salesforce_wrapper.egg-info/SOURCES.txt
salesforce_wrapper.egg-info/dependency_links.txt
salesforce_wrapper.egg-info/requires.txt
salesforce_wrapper.egg-info/top_level.txt