Metadata-Version: 1.2
Name: salesforce-wrapper
Version: 0.0.4
Summary: SalesForce wrapper
Home-page: https://github.com/bzdvdn/salesforce-wrapper.git
Author: bzdvdn
Author-email: bzdv.dn@gmail.com
License: MIT
Platform: UNKNOWN
Requires-Python: >=3.6
